tap_stackexchange/__init__.py
tap_stackexchange/__main__.py
tap_stackexchange/client.py
tap_stackexchange/streams.py
tap_stackexchange/tap.py
tap_stackexchange-0.0.12.dist-info/METADATA
tap_stackexchange-0.0.12.dist-info/WHEEL
tap_stackexchange-0.0.12.dist-info/entry_points.txt
tap_stackexchange-0.0.12.dist-info/licenses/LICENSE
tap_stackexchange-0.0.12.dist-info/RECORD
