Metadata-Version: 2.4
Name: tap-stackexchange
Version: 0.0.12
Summary: Singer tap for StackExchange, built with the Meltano SDK for Singer Taps.
Project-URL: Documentation, https://github.com/MeltanoLabs/tap-stackexchange/blob/main/README.md
Project-URL: Homepage, https://github.com/MeltanoLabs/tap-stackexchange
Project-URL: Repository, https://github.com/MeltanoLabs/tap-stackexchange
Author-email: Edgar Ramírez-Mondragón <edgarrm358@gmail.com>
License-Expression: Apache-2.0
License-File: LICENSE
Keywords: ELT,StackExchange,meltano,singer-io
Classifier: Programming Language :: Python :: 3 :: Only
Classifier: Programming Language :: Python :: 3.10
Classifier: Programming Language :: Python :: 3.11
Classifier: Programming Language :: Python :: 3.12
Classifier: Programming Language :: Python :: 3.13
Classifier: Programming Language :: Python :: 3.14
Requires-Python: >=3.10
Requires-Dist: pyrate-limiter==3.*; python_version < '4'
Requires-Dist: requests-cache==1.*; python_version < '4'
Requires-Dist: singer-sdk==0.53.*
Requires-Dist: typing-extensions>=4.15; python_full_version < '3.12'
